bing_cloud_search/CloudySearch.py
bing_cloud_search/__init__.py
bing_cloud_search-0.6.dist-info/DESCRIPTION.rst
bing_cloud_search-0.6.dist-info/METADATA
bing_cloud_search-0.6.dist-info/RECORD
bing_cloud_search-0.6.dist-info/WHEEL
bing_cloud_search-0.6.dist-info/metadata.json
bing_cloud_search-0.6.dist-info/top_level.txt
