Metadata-Version: 2.0
Name: bing-cloud-search
Version: 0.6
Summary: A method of turning search terms into wordclouds.
Home-page: https://github.com/tim-shane/cloudy_search
Author: Tim Edwards
Author-email: timedwards8@gmail.com
License: BSD
Keywords: wordcloud search Bing
Platform: UNKNOWN
Classifier: Development Status :: 3 - Alpha
Classifier: Topic :: Utilities
Requires-Dist: matplotlib
Requires-Dist: numpy
Requires-Dist: py-ms-cognitive
Requires-Dist: wordcloud
